LICENSE.txt
MANIFEST.in
README.rst
pyproject.toml
setup.py
tutor_ecommerce.egg-info/PKG-INFO
tutor_ecommerce.egg-info/SOURCES.txt
tutor_ecommerce.egg-info/dependency_links.txt
tutor_ecommerce.egg-info/entry_points.txt
tutor_ecommerce.egg-info/requires.txt
tutor_ecommerce.egg-info/top_level.txt
tutorecommerce/__about__.py
tutorecommerce/__init__.py
tutorecommerce/plugin.py
tutorecommerce/patches/caddyfile
tutorecommerce/patches/k8s-deployments
tutorecommerce/patches/k8s-jobs
tutorecommerce/patches/k8s-services
tutorecommerce/patches/kustomization-configmapgenerator
tutorecommerce/patches/local-docker-compose-caddy-aliases
tutorecommerce/patches/local-docker-compose-dev-services
tutorecommerce/patches/local-docker-compose-jobs-services
tutorecommerce/patches/local-docker-compose-services
tutorecommerce/patches/mfe-dockerfile-pre-npm-build-orders
tutorecommerce/patches/openedx-lms-common-settings
tutorecommerce/patches/openedx-lms-development-settings
tutorecommerce/patches/openedx-lms-production-settings
tutorecommerce/templates/ecommerce/apps/ecommerce-worker/settings/__init__.py
tutorecommerce/templates/ecommerce/apps/ecommerce-worker/settings/production.py
tutorecommerce/templates/ecommerce/apps/ecommerce/settings/__init__.py
tutorecommerce/templates/ecommerce/apps/ecommerce/settings/development.py
tutorecommerce/templates/ecommerce/apps/ecommerce/settings/paymentprocessors.json
tutorecommerce/templates/ecommerce/apps/ecommerce/settings/production.py
tutorecommerce/templates/ecommerce/apps/ecommerce/settings/partials/common.py
tutorecommerce/templates/ecommerce/build/ecommerce/Dockerfile
tutorecommerce/templates/ecommerce/build/ecommerce/assets.py
tutorecommerce/templates/ecommerce/build/ecommerce-worker/Dockerfile
tutorecommerce/templates/ecommerce/build/ecommerce/requirements/private-sample.txt
tutorecommerce/templates/ecommerce/tasks/ecommerce/init
tutorecommerce/templates/ecommerce/tasks/lms/init
tutorecommerce/templates/ecommerce/tasks/mysql/init